LICENSE
MANIFEST.in
README.md
pyproject.toml
requirements.txt
setup.py
src/torch_linear_assignment.cpp
src/torch_linear_assignment_cuda.cpp
src/torch_linear_assignment_cuda_kernel.cu
torch_linear_assignment/__init__.py
torch_linear_assignment/assignment.py
torch_linear_assignment.egg-info/PKG-INFO
torch_linear_assignment.egg-info/SOURCES.txt
torch_linear_assignment.egg-info/dependency_links.txt
torch_linear_assignment.egg-info/requires.txt
torch_linear_assignment.egg-info/top_level.txt