Metadata-Version: 2.4
Name: torch-linear-assignment
Version: 0.0.5
Summary: Batched linear assignment with PyTorch and CUDA.
Author: Ivan Karpukhin
Author-email: karpuhini@yandex.ru
License-File: LICENSE
Requires-Dist: torch>=1.12.0
Requires-Dist: scipy>=1.6.0
Dynamic: author
Dynamic: author-email
Dynamic: description
Dynamic: description-content-type
Dynamic: license-file
Dynamic: requires-dist
Dynamic: summary
